biobb_flexdyn/__init__.py
biobb_flexdyn/py.typed
biobb_flexdyn/flexdyn/__init__.py
biobb_flexdyn/flexdyn/concoord_disco.py
biobb_flexdyn/flexdyn/concoord_dist.py
biobb_flexdyn/flexdyn/imod_imc.py
biobb_flexdyn/flexdyn/imod_imode.py
biobb_flexdyn/flexdyn/imod_imove.py
biobb_flexdyn/flexdyn/nolb_nma.py
biobb_flexdyn/flexdyn/prody_anm.py
biobb_flexdyn-5.2.0.dist-info/licenses/LICENSE
biobb_flexdyn-5.2.0.dist-info/METADATA
biobb_flexdyn-5.2.0.dist-info/WHEEL
biobb_flexdyn-5.2.0.dist-info/entry_points.txt
biobb_flexdyn-5.2.0.dist-info/top_level.txt
biobb_flexdyn-5.2.0.dist-info/RECORD
