Metadata-Version: 2.4
Name: biobb_flexdyn
Version: 5.2.0
Summary: biobb_flexdyn is a BioBB category for studies on the conformational landscape of native proteins.
Home-page: https://github.com/bioexcel/biobb_flexdyn
Author: Biobb developers
Author-email: adam.hospital@irbbarcelona.org
Project-URL: Documentation, http://biobb-flexdyn.readthedocs.io/en/latest/
Project-URL: Bioexcel, https://bioexcel.eu/
Keywords: 3D-Bioinfo ELIXIR FlexDyn Bioinformatics Workflows BioExcel Compatibility Flexibility Ensembles Protein Structure
Classifier: Development Status :: 5 - Production/Stable
Classifier: Programming Language :: Python :: 3.10
Classifier: License :: OSI Approved :: Apache Software License
Classifier: Operating System :: MacOS :: MacOS X
Classifier: Operating System :: POSIX
Requires-Python: >=3.10,<3.12
License-File: LICENSE
Requires-Dist: biobb_common==5.2.0
Requires-Dist: scipy<1.14.0,>=1.13.0
Dynamic: author
Dynamic: author-email
Dynamic: classifier
Dynamic: description
Dynamic: description-content-type
Dynamic: home-page
Dynamic: keywords
Dynamic: license-file
Dynamic: project-url
Dynamic: requires-dist
Dynamic: requires-python
Dynamic: summary
